genalog/__init__.py
genalog/pipeline.py
genalog/degradation/__init__.py
genalog/degradation/degrader.py
genalog/degradation/effect.py
genalog/generation/__init__.py
genalog/generation/content.py
genalog/generation/document.py
genalog/generation/templates/base.css.jinja
genalog/generation/templates/base.html.jinja
genalog/generation/templates/columns.css.jinja
genalog/generation/templates/columns.html.jinja
genalog/generation/templates/letter.css.jinja
genalog/generation/templates/letter.html.jinja
genalog/generation/templates/text_block.css.jinja
genalog/generation/templates/text_block.html.jinja
genalog/generation/templates/macro/dimension.css.jinja
genalog/generation/templates/macro/page_layout.css.jinja
genalog/generation/templates/macro/text.css.jinja
genalog/ocr/__init__.py
genalog/ocr/blob_client.py
genalog/ocr/common.py
genalog/ocr/grok.py
genalog/ocr/metrics.py
genalog/ocr/rest_client.py
genalog/text/__init__.py
genalog/text/alignment.py
genalog/text/anchor.py
genalog/text/conll_format.py
genalog/text/lcs.py
genalog/text/ner_label.py
genalog/text/preprocess.py
genalog/text/splitter.py
genalog-0.1.0.dist-info/LICENSE
genalog-0.1.0.dist-info/METADATA
genalog-0.1.0.dist-info/WHEEL
genalog-0.1.0.dist-info/top_level.txt
genalog-0.1.0.dist-info/RECORD
