Metadata-Version: 2.1
Name: genalog
Version: 0.1.0
Summary: Tools for generating analog document (images) from raw text
Home-page: https://github.com/microsoft/genalog
Author: Jianjie Liu & Amit Gupte
Author-email: ta_maidap_fy20_h2@microsoft.com
License: UNKNOWN
Platform: UNKNOWN
Classifier: Programming Language :: Python :: 3
Classifier: Operating System :: OS Independent
Requires-Python: >=3.6
Requires-Dist: biopython (==1.76)
Requires-Dist: numpy (==1.18.1)
Requires-Dist: python-dotenv (==0.11.0)
Requires-Dist: requests (==2.23.0)
Requires-Dist: azure-core (==1.10.0)
Requires-Dist: azure-common (==1.1.26)
Requires-Dist: azure-storage-blob (==12.3.1)
Requires-Dist: tqdm (==4.43.0)
Requires-Dist: Jinja2 (==2.11.1)
Requires-Dist: WeasyPrint (==51)
Requires-Dist: matplotlib (==3.2.1)
Requires-Dist: scikit-image (==0.16.2)
Requires-Dist: opencv-python (==4.2.0.34)
Requires-Dist: pandas (==1.0.1)
Requires-Dist: aiofiles (==0.5.0)
Requires-Dist: aiohttp (==3.6.2)
